{
    "levels": [
        {
          "spawns": [
            {
              "distance": -3,
              "positionX": 2,
              "name": "spearman"
            },
            {
              "distance": -3,
              "positionX": -2,
              "name": "spearman"
            },
            {
              "distance": -5,
              "positionX": -1.5,
              "name": "spearman"
            },
            {
              "distance": -6,
              "positionX": 1.5,
              "name": "spearman"
            },
            {
              "distance": -10,
              "positionX": 4,
              "name": "spearman"
            },
            {
              "distance": -10,
              "positionX": -4,
              "name": "spearman"
            },
            {
              "distance": -15,
              "positionX": -1,
              "name": "spearman"
            },
            {
              "distance": -25,
              "positionX": 1,
              "name": "swordsman"
            }

          ]

        }

    ]
}